dhenara/__init__.py
dhenara-1.0.3.dist-info/licenses/LICENSE
dhenara-1.0.3.dist-info/METADATA
dhenara-1.0.3.dist-info/WHEEL
dhenara-1.0.3.dist-info/top_level.txt
dhenara-1.0.3.dist-info/RECORD
