Metadata-Version: 2.4
Name: dhenara
Version: 1.0.3
Summary: DEPRECATED: Please use dhenara-ai instead
Home-page: https://github.com/dhenara/dhenara-ai
Author: Dhenara
Author-email: support@dhenara.com
License: MIT
Project-URL: Homepage, https://dhenara.com
Project-URL: Documentation, https://docs.dhenara.com/
Project-URL: Bug Reports, https://github.com/dhenara/dhenara-ai/issues
Project-URL: Source Code, https://github.com/dhenara/dhenara-ai
Keywords: ai,llm,machine learning,language models
Classifier: Intended Audience :: Developers
Classifier: Programming Language :: Python :: 3
Classifier: Programming Language :: Python :: 3.10
Classifier: Operating System :: OS Independent
Classifier: Topic :: Scientific/Engineering :: Artificial Intelligence
Classifier: License :: OSI Approved :: MIT License
Requires-Python: >=3.10
License-File: LICENSE
Requires-Dist: dhenara-ai>=1.0.0
Dynamic: author
Dynamic: author-email
Dynamic: classifier
Dynamic: description
Dynamic: description-content-type
Dynamic: home-page
Dynamic: keywords
Dynamic: license
Dynamic: license-file
Dynamic: project-url
Dynamic: requires-dist
Dynamic: requires-python
Dynamic: summary
